docserve/__init__.py
docserve/docserve.py
docserve/logo.png
docserve/docs/home.md
docserve/docs/demo/code.md
docserve/docs/demo/dowloads.md
docserve/docs/demo/images.md
docserve/docs/demo/lists.md
docserve/docs/demo/metadata.md
docserve/docs/demo/tables.md
docserve/docs/demo/text.md
docserve/docs/demo/assets/Thumbnail_Preview_Test.pptx
docserve/docs/demo/assets/big_buck_bunny.ogv
docserve/docs/demo/assets/example.csv
docserve/docs/demo/assets/example.docx
docserve/docs/demo/assets/example.pdf
docserve/docs/demo/assets/images-05a8fd7e.png
docserve/docs/demo/assets/images-95cf4590.png
docserve/docs/demo/assets/relative-link.md
docserve/docs/items/medkit.md
docserve/docs/items/touchscreen.md
docserve/docs/items/assets/medkit-92c01446.png
docserve/docs/items/assets/touchscreen-2540530e.png
docserve/docs/items/assets/touchscreen-93af13f6.png
docserve/docs/items/assets/touchscreen-9cd51c52.png
docserve/style/static/default.css
docserve/style/static/default.scss
docserve/style/static/fonts/FontAwesome.otf
docserve/style/static/fonts/fontawesome-webfont.eot
docserve/style/static/fonts/fontawesome-webfont.svg
docserve/style/static/fonts/fontawesome-webfont.ttf
docserve/style/static/fonts/fontawesome-webfont.woff
docserve/style/static/fonts/fontawesome-webfont.woff2
docserve/style/static/lib/bootbox-4.4.0.min.js
docserve/style/static/lib/bootstrap-4.0.0.min.css
docserve/style/static/lib/bootstrap-4.0.0.min.js
docserve/style/static/lib/font-awesome-4.7.0.min.css
docserve/style/static/lib/highlight-9.12.0.min.js
docserve/style/static/lib/highlightjs-9.12.0.min.css
docserve/style/static/lib/jquery-3.2.1.slim.min.js
docserve/style/templates/404.html
docserve/style/templates/base.html
docserve/style/templates/document.html
docserve/style/templates/haxxor.html
docserve/style/templates/part.html
docserve/style/templates/print_footer.html
docserve/style/templates/print_header.html
docserve-0.9.7.dist-info/METADATA
docserve-0.9.7.dist-info/RECORD
docserve-0.9.7.dist-info/WHEEL
docserve-0.9.7.dist-info/entry_points.txt
docserve-0.9.7.dist-info/top_level.txt
