Metadata-Version: 2.1
Name: docserve
Version: 0.9.7
Summary: A tool for quick and easy Markdown project documentation.
Home-page: https://github.com/HEInventions/DocServe
Author: Hardy & Ellis Inventions LTD
Author-email: support@heinventions.com
License: UNKNOWN
Platform: UNKNOWN
Classifier: Programming Language :: Python :: 3
Classifier: License :: OSI Approved :: MIT License
Requires-Python: >=3.6.0
Requires-Dist: Flask (==1.0.2)
Requires-Dist: Markdown (==2.6.11)
Requires-Dist: timeago (==1.0.8)
Requires-Dist: Frozen-Flask (==0.15)
Requires-Dist: beautifulsoup4 (==4.6.3)
Requires-Dist: requests (==2.19.1)
